django_gradual_throttle/__init__.py
django_gradual_throttle/apps.py
django_gradual_throttle/defaults.py
django_gradual_throttle/middleware.py
django_gradual_throttle/settings.py
django_gradual_throttle/utils.py
django_gradual_throttle/strategies/__init__.py
django_gradual_throttle/strategies/base.py
django_gradual_throttle/strategies/exponential.py
django_gradual_throttle/strategies/linear.py
django_gradual_throttle/tests/__init__.py
django_gradual_throttle/tests/test_middleware.py
django_gradual_throttle/tests/test_settings.py
django_gradual_throttle/tests/test_utils.py
django_gradual_throttle-1.0.3.dist-info/licenses/LICENSE
django_gradual_throttle-1.0.3.dist-info/METADATA
django_gradual_throttle-1.0.3.dist-info/WHEEL
django_gradual_throttle-1.0.3.dist-info/top_level.txt
django_gradual_throttle-1.0.3.dist-info/RECORD
