Metadata-Version: 2.4
Name: django-gradual-throttle
Version: 1.0.3
Summary: Django middleware for gradual request throttling with configurable delay strategies
Home-page: https://github.com/Dhruvpatel004/django-gradual-throttle
Author: Dhruv Patel
Author-email: Django Gradual Throttle Team <support@example.com>
License: MIT
Project-URL: Homepage, https://github.com/Dhruvpatel004/django_gradual_throttle
Project-URL: Documentation, https://github.com/Dhruvpatel004/django_gradual_throttle
Project-URL: Repository, https://github.com/Dhruvpatel004/django_gradual_throttle
Project-URL: Bug Reports, https://github.com/Dhruvpatel004/django_gradual_throttle
Keywords: django,middleware,throttling,rate-limiting,gradual,delay
Classifier: Development Status :: 5 - Production/Stable
Classifier: Environment :: Web Environment
Classifier: Framework :: Django
Classifier: Framework :: Django :: 3.2
Classifier: Framework :: Django :: 4.0
Classifier: Framework :: Django :: 4.1
Classifier: Framework :: Django :: 4.2
Classifier: Framework :: Django :: 5.0
Classifier: Intended Audience :: Developers
Classifier: License :: OSI Approved :: MIT License
Classifier: Operating System :: OS Independent
Classifier: Programming Language :: Python
Classifier: Programming Language :: Python :: 3
Classifier: Programming Language :: Python :: 3.8
Classifier: Programming Language :: Python :: 3.9
Classifier: Programming Language :: Python :: 3.10
Classifier: Programming Language :: Python :: 3.11
Classifier: Programming Language :: Python :: 3.12
Classifier: Topic :: Internet :: WWW/HTTP
Classifier: Topic :: Internet :: WWW/HTTP :: Dynamic Content
Classifier: Topic :: Software Development :: Libraries :: Python Modules
Requires-Python: >=3.8
License-File: LICENSE
Requires-Dist: Django>=3.2
Provides-Extra: dev
Requires-Dist: pytest>=6.0; extra == "dev"
Requires-Dist: pytest-django>=4.0; extra == "dev"
Requires-Dist: pytest-cov>=2.0; extra == "dev"
Requires-Dist: black>=22.0; extra == "dev"
Requires-Dist: flake8>=4.0; extra == "dev"
Requires-Dist: isort>=5.0; extra == "dev"
Requires-Dist: mypy>=0.900; extra == "dev"
Provides-Extra: redis
Requires-Dist: redis>=3.0; extra == "redis"
Requires-Dist: django-redis>=5.0; extra == "redis"
Dynamic: author
Dynamic: home-page
Dynamic: license-file
Dynamic: requires-python
